generic_table/__init__.py
generic_table/generic_table.py
generic_table-1.1.5.dist-info/METADATA
generic_table-1.1.5.dist-info/WHEEL
generic_table-1.1.5.dist-info/licenses/LICENSE
generic_table-1.1.5.dist-info/RECORD
