Metadata-Version: 2.4
Name: generic-table
Version: 1.1.5
Author-email: TechServ Engineering Team <engineering@techserv.com>
License-Expression: MIT
License-File: LICENSE
Requires-Python: >=3.12
Requires-Dist: django<6.0.0,>=5.1.5
Requires-Dist: openpyxl<4.0.0,>=3.1.3
Provides-Extra: dev
Requires-Dist: coverage; extra == 'dev'
Requires-Dist: psycopg; extra == 'dev'
Requires-Dist: pytest; extra == 'dev'
Requires-Dist: pytest-cov; extra == 'dev'
Requires-Dist: pytest-django; extra == 'dev'
